COV_brain_tumor_detection/__init__.py
COV_brain_tumor_detection/config.py
COV_brain_tumor_detection/histories/model_efficientnet_history.pkl
COV_brain_tumor_detection/histories/model_mnasnet_history.pkl
COV_brain_tumor_detection/histories/model_vgg16_history.pkl
COV_brain_tumor_detection/models/__init__.py
COV_brain_tumor_detection/models/models.py
COV_brain_tumor_detection/preprocessing/__init__.py
COV_brain_tumor_detection/preprocessing/data_loaders.py
COV_brain_tumor_detection/preprocessing/data_preparation.py
COV_brain_tumor_detection/utils/__init__.py
COV_brain_tumor_detection/utils/data_utils.py
COV_brain_tumor_detection/visualization/__init__.py
COV_brain_tumor_detection/visualization/plot_results.py
cov_brain_tumor_detection-1.1.0.dist-info/METADATA
cov_brain_tumor_detection-1.1.0.dist-info/WHEEL
cov_brain_tumor_detection-1.1.0.dist-info/RECORD
